{
  "main": {
    "id": "f02aab9ffc12ae5a",
    "type": "split",
    "children": [
      {
        "id": "e147ca1f63bfa8e7",
        "type": "tabs",
        "children": [
          {
            "id": "8b87629f6593b64b",
            "type": "leaf",
            "state": {
              "type": "markdown",
              "state": {
                "file": "笔记/我的学习笔记（视频）/2026-04-19 lvgl学习.md",
                "mode": "source",
                "source": false
              },
              "icon": "lucide-file",
              "title": "2026-04-19 lvgl学习"
            }
          }
        ]
      }
    ],
    "direction": "vertical"
  },
  "left": {
    "id": "84d24ea38ff7cad7",
    "type": "split",
    "children": [
      {
        "id": "95bb53d49c30c7db",
        "type": "tabs",
        "children": [
          {
            "id": "352778fe4a983708",
            "type": "leaf",
            "state": {
              "type": "file-explorer",
              "state": {
                "sortOrder": "alphabetical",
                "autoReveal": false
              },
              "icon": "lucide-folder-closed",
              "title": "文件列表"
            }
          },
          {
            "id": "454854312f079496",
            "type": "leaf",
            "state": {
              "type": "search",
              "state": {
                "query": "path:\"笔记/\" ",
                "matchingCase": false,
                "explainSearch": false,
                "collapseAll": false,
                "extraContext": false,
                "sortOrder": "alphabetical"
              },
              "icon": "lucide-search",
              "title": "搜索"
            }
          },
          {
            "id": "f7c1a9f4ce9778b7",
            "type": "leaf",
            "state": {
              "type": "bookmarks",
              "state": {},
              "icon": "lucide-bookmark",
              "title": "书签"
            }
          }
        ]
      }
    ],
    "direction": "horizontal",
    "width": 311.5
  },
  "right": {
    "id": "a10ed8c37f5a1e6a",
    "type": "split",
    "children": [
      {
        "id": "3ed833f54a3825e3",
        "type": "tabs",
        "children": [
          {
            "id": "b62e21d933c3452d",
            "type": "leaf",
            "state": {
              "type": "backlink",
              "state": {
                "file": "笔记/我的学习笔记/LVGL/02、父级与子级.md",
                "collapseAll": false,
                "extraContext": false,
                "sortOrder": "alphabetical",
                "showSearch": false,
                "searchQuery": "",
                "backlinkCollapsed": false,
                "unlinkedCollapsed": true
              },
              "icon": "links-coming-in",
              "title": "02、父级与子级 的反向链接列表"
            }
          },
          {
            "id": "74ad0f045a7c6b2f",
            "type": "leaf",
            "state": {
              "type": "outgoing-link",
              "state": {
                "file": "未命名.md",
                "linksCollapsed": false,
                "unlinkedCollapsed": true
              },
              "icon": "links-going-out",
              "title": "未命名 的出链列表"
            }
          },
          {
            "id": "d0faa38100442c56",
            "type": "leaf",
            "state": {
              "type": "tag",
              "state": {
                "sortOrder": "frequency",
                "useHierarchy": true,
                "showSearch": false,
                "searchQuery": ""
              },
              "icon": "lucide-tags",
              "title": "标签"
            }
          },
          {
            "id": "05bd98a7614dc42d",
            "type": "leaf",
            "state": {
              "type": "all-properties",
              "state": {
                "sortOrder": "frequency",
                "showSearch": false,
                "searchQuery": ""
              },
              "icon": "lucide-archive",
              "title": "添加笔记属性"
            }
          },
          {
            "id": "aa4b602c9a16e588",
            "type": "leaf",
            "state": {
              "type": "outline",
              "state": {
                "file": "未命名.md",
                "followCursor": false,
                "showSearch": false,
                "searchQuery": ""
              },
              "icon": "lucide-list",
              "title": "未命名 的大纲"
            }
          }
        ]
      }
    ],
    "direction": "horizontal",
    "width": 300,
    "collapsed": true
  },
  "left-ribbon": {
    "hiddenItems": {
      "switcher:打开快速切换": false,
      "graph:查看关系图谱": false,
      "canvas:新建白板": false,
      "daily-notes:打开/创建今天的日记": false,
      "templates:插入模板": false,
      "command-palette:打开命令面板": false,
      "bases:新建数据库": false
    }
  },
  "active": "8b87629f6593b64b",
  "lastOpenFiles": [
    "reorganize.ps1",
    "reorganize.ps1.tmp.13284.9e14de8d594c",
    "笔记/我的学习笔记/TFT屏幕MIPI-DSI驱动原理.md",
    "笔记/我的学习笔记（视频）/2026-04-19 lvgl学习.md",
    "高昌/TAS-LTE-892D_s4 4G DTU 使用教程.md",
    "高昌/TAS-LTE-892D_s4 AT指令与STM32双向通信教程.md",
    "高昌/GcCarLifts GitHub组织全部仓库目录详解.md",
    "笔记/我的学习笔记/网络笔记/NAT与DHCP.md",
    "笔记/我的学习笔记/网络笔记/MQTT.md",
    "笔记/我的学习笔记/电路学习笔记/继电器电源开关设计要点.md",
    "笔记/我的学习笔记/电路学习笔记/电路学习笔记索引.md",
    "笔记/我的学习笔记/电路学习笔记/电路学习笔记索引.md.tmp.72800.5a5f77a62380",
    "笔记/我的学习笔记/电路学习笔记/电路基础入门.md",
    "笔记/我的学习笔记/电路学习笔记/电路基础入门.md.tmp.72800.fcdb04ec02f3",
    "笔记/我的学习笔记/电路学习笔记/场效应管基础.md",
    "笔记/我的学习笔记/电路学习笔记/场效应管基础.md.tmp.72800.1fd6d3b630cd",
    "笔记/我的学习笔记/电路学习笔记/三极管基础.md",
    "笔记/我的学习笔记/电路学习笔记/三极管基础.md.tmp.72800.7f26f47df8f2",
    "笔记/我的学习笔记/电路学习笔记/二极管基础.md",
    "笔记/我的学习笔记/电路学习笔记/二极管基础.md.tmp.72800.e0db3a16f4c1",
    "智能家居/项目交接日志.md",
    "智能家居/ESP32-P4小智智能家居国一完整迭代方案.md",
    "笔记/2x12横表模板.md",
    "笔记/linux网络学习.md",
    "笔记/我的学习笔记/LVGL移植ESP32-P4完整指南.md",
    "笔记/我的学习笔记/Linux网络排障知识详解.md",
    "笔记/我的学习笔记/网络笔记/ESP32网络开发实战.md",
    "笔记/我的学习笔记/网络笔记/HTTP与HTTPS协议.md",
    "笔记/我的学习笔记/网络笔记/ARP与ICMP协议.md",
    "笔记/我的学习笔记/网络笔记/物联网协议概览.md",
    "笔记/我的学习笔记/网络笔记/网络调试工具.md",
    "笔记/我的学习笔记/网络笔记/小智项目mqtt设计架构.md",
    "笔记/我的学习笔记/硬件外设/MSPM0G3507电源与滤波设计",
    "英语笔记/CET4-单词闪卡.html",
    "笔记/ai工作日志记忆/2026-05-20",
    "笔记/我的学习笔记/电路学习笔记",
    "Pasted image 20260509202121.png",
    "Pasted image 20260509165257.png",
    "Pasted image 20260509165211.png",
    "未命名.canvas"
  ]
}